Changelog
LICENSE
MANIFEST.in
README.md
VERSION
setup.py
puka/__init__.py
puka/channel.py
puka/client.py
puka/compat.py
puka/connection.py
puka/exceptions.py
puka/machine.py
puka/poll.py
puka/promise.py
puka/simplebuffer.py
puka/spec.py
puka/spec_exceptions.py
puka/table.py
puka/urlparse.py
puka.egg-info/PKG-INFO
puka.egg-info/SOURCES.txt
puka.egg-info/dependency_links.txt
puka.egg-info/requires.txt
puka.egg-info/top_level.txt
puka.egg-info/zip-safe