Metadata-Version: 1.1
Name: puka
Version: 0.0.8
Summary: Puka - the opinionated RabbitMQ client
Home-page: http://github.com/majek/puka#readme
Author: Marek Majkowski
Author-email: marek@popcount.org
License: MIT
Platform: any
Classifier: Development Status :: 3 - Alpha
Classifier: Intended Audience :: Developers
Classifier: License :: OSI Approved :: MIT License
Classifier: Operating System :: OS Independent
Classifier: Topic :: Software Development :: Libraries :: Python Modules
Classifier: Programming Language :: Python :: 2.7
Classifier: Programming Language :: Python :: 3.6
Classifier: Programming Language :: Python :: 3.7
Classifier: Programming Language :: Python :: 3.8
